Metadata-Version: 2.1
Name: pulumi-aws-s3-replicated-bucket
Version: 0.0.6
Summary: UNKNOWN
Home-page: UNKNOWN
License: UNKNOWN
Platform: UNKNOWN
